flow-sdk-utils/NumpyEncoder.py
flow-sdk-utils/__init__.py
flow-sdk-utils/rpc_server.py
src/NumpyEncoder.py
src/__init__.py
src/rpc_server.py
utils/NumpyEncoder.py
utils/__init__.py
utils/rpc_server.py
flow_sdk_utils-1.0.1.dist-info/METADATA
flow_sdk_utils-1.0.1.dist-info/WHEEL
flow_sdk_utils-1.0.1.dist-info/top_level.txt
flow_sdk_utils-1.0.1.dist-info/RECORD
