Metadata-Version: 2.1
Name: flow-sdk-utils
Version: 1.0.1
Summary: Python utils for HahnPRO Flow-SDK
Home-page: https://gitlab.com/tklingenhoefer/flow-sdk-utils
Author: Timo Klingenhöfer
Author-email: tk@hahnpro.com
License: MIT
Platform: UNKNOWN
Classifier: License :: OSI Approved :: MIT License
Classifier: Programming Language :: Python :: 3
Classifier: Programming Language :: Python :: 3.7
Requires-Dist: pika
Requires-Dist: numpy
